openapify/__init__.py
openapify/decorators.py
openapify/plugin.py
openapify/py.typed
openapify/core/__init__.py
openapify/core/base_plugins.py
openapify/core/builder.py
openapify/core/const.py
openapify/core/document.py
openapify/core/models.py
openapify/core/utils.py
openapify/core/openapi/__init__.py
openapify/core/openapi/models.py
openapify/ext/__init__.py
openapify/ext/web/__init__.py
openapify/ext/web/aiohttp.py
openapify-0.7.dist-info/licenses/LICENSE
openapify-0.7.dist-info/METADATA
openapify-0.7.dist-info/WHEEL
openapify-0.7.dist-info/top_level.txt
openapify-0.7.dist-info/RECORD
