Metadata-Version: 2.4
Name: openapify
Version: 0.7
Summary: Framework agnostic OpenAPI Specification generation for code lovers
Home-page: https://github.com/Fatal1ty/openapify
Author: Alexander Tikhonov
Author-email: random.gauss@gmail.com
License: Apache License, Version 2.0
Platform: all
Classifier: License :: OSI Approved :: Apache Software License
Classifier: Intended Audience :: Developers
Classifier: Programming Language :: Python :: 3 :: Only
Classifier: Programming Language :: Python :: 3.9
Classifier: Programming Language :: Python :: 3.10
Classifier: Programming Language :: Python :: 3.11
Classifier: Programming Language :: Python :: 3.12
Classifier: Programming Language :: Python :: 3.13
Classifier: Development Status :: 3 - Alpha
Requires-Python: >=3.8
License-File: LICENSE
Requires-Dist: apispec
Requires-Dist: mashumaro>=3.15
Provides-Extra: aiohttp
Requires-Dist: aiohttp; extra == "aiohttp"
Dynamic: author
Dynamic: author-email
Dynamic: classifier
Dynamic: description
Dynamic: description-content-type
Dynamic: home-page
Dynamic: license
Dynamic: license-file
Dynamic: platform
Dynamic: provides-extra
Dynamic: requires-dist
Dynamic: requires-python
Dynamic: summary
